setup.py
termimg.py
termimg.egg-info/PKG-INFO
termimg.egg-info/SOURCES.txt
termimg.egg-info/dependency_links.txt
termimg.egg-info/top_level.txt