Metadata-Version: 1.0
Name: termimg
Version: 1.0.3
Summary: render raster images to the terminal
Home-page: https://github.com/frnsys/termimg
Author: Francis Tseng (@frnsys)
Author-email: f@frnsys.com
License: MIT
Platform: UNKNOWN
